argofamiglia/CONSTANTS.py
argofamiglia/__init__.py
argofamiglia/argofamiglia.py
argofamiglia/auth.py
argofamiglia-0.1.2.dist-info/LICENSE
argofamiglia-0.1.2.dist-info/METADATA
argofamiglia-0.1.2.dist-info/WHEEL
argofamiglia-0.1.2.dist-info/top_level.txt
argofamiglia-0.1.2.dist-info/RECORD
