Metadata-Version: 2.1
Name: argofamiglia
Version: 0.1.2
Summary: An API wrapper created to interface Python with Argo ScuolaNext.
Home-page: https://github.com/salvatore-abello/argofamiglia
Author: Salvatore Abello
Author-email: salvatore.abello2005@gmail.com
Project-URL: Homepage, https://github.com/salvatore-abello/argofamiglia
Keywords: argofamiglia argo argoscuolanext python scuolanext
Classifier: Programming Language :: Python :: 3
Classifier: License :: OSI Approved :: MIT License
Classifier: Operating System :: OS Independent
Requires-Python: >=3.8
License-File: LICENSE
Requires-Dist: requests
